mycliapp/__init__.py
mycliapp/main.py
mycliapp1-0.1.dist-info/METADATA
mycliapp1-0.1.dist-info/WHEEL
mycliapp1-0.1.dist-info/entry_points.txt
mycliapp1-0.1.dist-info/top_level.txt
mycliapp1-0.1.dist-info/RECORD
